setux/actions/admin.py
setux/actions/file.py
setux/actions/host.py
setux/actions/misc.py
setux/actions/module.py
setux/actions/transfer.py
setux/actions/updater.py
setux/actions/user.py
setux_actions-0.2503.1.dist-info/METADATA
setux_actions-0.2503.1.dist-info/WHEEL
setux_actions-0.2503.1.dist-info/top_level.txt
setux_actions-0.2503.1.dist-info/RECORD
