Metadata-Version: 2.2
Name: setux_actions
Version: 0.2503.1
Summary: System deployment
Author-email: Louis RIVIERE <louis@riviere.xyz>
License: MIT
Project-URL: pypi, https://pypi.org/project/setux-actions
Project-URL: repository, https://notabug.org/dugres/setux_actions
Keywords: utility
Classifier: Development Status :: 3 - Alpha
Classifier: License :: OSI Approved :: MIT License
Classifier: Programming Language :: Python :: 3
Classifier: Operating System :: POSIX :: Linux
Classifier: Environment :: Console
Classifier: Intended Audience :: Developers
Classifier: Intended Audience :: Information Technology
Classifier: Intended Audience :: System Administrators
Classifier: Topic :: System :: Installation/Setup
Classifier: Topic :: System :: Systems Administration
Classifier: Topic :: Utilities
Requires-Python: >=3.9
Requires-Dist: setux_core>=0.2502.0
Requires-Dist: pybrary>=0.2452.0
